{"type": "FeatureCollection", "features": [                                  
  {"type":"Feature","properties":{"EMD_CD":"47250101","EMD_ENG_NM":"Seongha-dong","EMD_KOR_NM":"성하동"},"geometry":{"type":"Polygon","coordinates":[[[128.165,36.416],[128.163,36.414],[128.163,36.415],[128.163,36.416],[128.165,36.416]]]}},                  
  {"type":"Feature","properties":{"EMD_CD":"47250102","EMD_ENG_NM":"Seongdong-dong","EMD_KOR_NM":"성동동"},"geometry":{"type":"Polygon","coordinates":[[[128.183,36.418],[128.171,36.403],[128.163,36.407],[128.163,36.414],[128.165,36.416],[128.166,36.417],[128.183,36.418]]]}},                  
  {"type":"Feature","properties":{"EMD_CD":"47250103","EMD_ENG_NM":"Inbong-dong","EMD_KOR_NM":"인봉동"},"geometry":{"type":"Polygon","coordinates":[[[128.166,36.417],[128.165,36.416],[128.163,36.416],[128.163,36.419],[128.166,36.417]]]}},                  
  {"type":"Feature","properties":{"EMD_CD":"47250104","EMD_ENG_NM":"Bongnyong-dong","EMD_KOR_NM":"복룡동"},"geometry":{"type":"Polygon","coordinates":[[[128.2,36.428],[128.188,36.42],[128.183,36.418],[128.166,36.417],[128.163,36.419],[128.163,36.42],[128.177,36.422],[128.184,36.427],[128.192,36.429],[128.2,36.428]]]}},                  
  {"type":"Feature","properties":{"EMD_CD":"47250105","EMD_ENG_NM":"Naengnim-dong","EMD_KOR_NM":"냉림동"},"geometry":{"type":"Polygon","coordinates":[[[128.177,36.422],[128.163,36.42],[128.159,36.42],[128.158,36.428],[128.177,36.422]]]}},                  
  {"type":"Feature","properties":{"EMD_CD":"47250106","EMD_ENG_NM":"Seoseong-dong","EMD_KOR_NM":"서성동"},"geometry":{"type":"Polygon","coordinates":[[[128.163,36.419],[128.163,36.416],[128.163,36.415],[128.159,36.416],[128.159,36.42],[128.163,36.42],[128.163,36.419]]]}},                  
  {"type":"Feature","properties":{"EMD_CD":"47250107","EMD_ENG_NM":"Namseong-dong","EMD_KOR_NM":"남성동"},"geometry":{"type":"Polygon","coordinates":[[[128.159,36.416],[128.163,36.415],[128.163,36.414],[128.163,36.407],[128.158,36.408],[128.154,36.416],[128.159,36.416]]]}},                  
  {"type":"Feature","properties":{"EMD_CD":"47250108","EMD_ENG_NM":"Seomun-dong","EMD_KOR_NM":"서문동"},"geometry":{"type":"Polygon","coordinates":[[[128.159,36.42],[128.159,36.416],[128.154,36.416],[128.149,36.416],[128.159,36.42]]]}},                  
  {"type":"Feature","properties":{"EMD_CD":"47250109","EMD_ENG_NM":"Muyang-dong","EMD_KOR_NM":"무양동"},"geometry":{"type":"Polygon","coordinates":[[[128.159,36.42],[128.149,36.416],[128.149,36.416],[128.146,36.42],[128.158,36.428],[128.159,36.42]]]}},                  
  {"type":"Feature","properties":{"EMD_CD":"47250110","EMD_ENG_NM":"Nagyang-dong","EMD_KOR_NM":"낙양동"},"geometry":{"type":"Polygon","coordinates":[[[128.158,36.408],[128.154,36.405],[128.137,36.407],[128.133,36.413],[128.149,36.416],[128.149,36.416],[128.154,36.416],[128.158,36.408]]]}},                  
  {"type":"Feature","properties":{"EMD_CD":"47250111","EMD_ENG_NM":"Gaeun-dong","EMD_KOR_NM":"개운동"},"geometry":{"type":"Polygon","coordinates":[[[128.154,36.405],[128.145,36.394],[128.12,36.371],[128.115,36.396],[128.137,36.407],[128.154,36.405]]]}},                  
  {"type":"Feature","properties":{"EMD_CD":"47250112","EMD_ENG_NM":"Sinbong-dong","EMD_KOR_NM":"신봉동"},"geometry":{"type":"Polygon","coordinates":[[[128.163,36.407],[128.171,36.403],[128.17,36.403],[128.162,36.393],[128.157,36.386],[128.145,36.394],[128.154,36.405],[128.158,36.408],[128.163,36.407]]]}},                  
  {"type":"Feature","properties":{"EMD_CD":"47250113","EMD_ENG_NM":"Gajang-dong","EMD_KOR_NM":"가장동"},"geometry":{"type":"Polygon","coordinates":[[[128.157,36.386],[128.157,36.386],[128.154,36.381],[128.143,36.37],[128.135,36.366],[128.119,36.371],[128.12,36.371],[128.145,36.394],[128.157,36.386]]]}},                  
  {"type":"Feature","properties":{"EMD_CD":"47250114","EMD_ENG_NM":"Yangchon-dong","EMD_KOR_NM":"양촌동"},"geometry":{"type":"Polygon","coordinates":[[[128.143,36.37],[128.159,36.342],[128.135,36.366],[128.143,36.37]]]}},                  
  {"type":"Feature","properties":{"EMD_CD":"47250115","EMD_ENG_NM":"Jicheon-dong","EMD_KOR_NM":"지천동"},"geometry":{"type":"Polygon","coordinates":[[[128.183,36.354],[128.174,36.333],[128.173,36.334],[128.171,36.335],[128.159,36.342],[128.143,36.37],[128.154,36.381],[128.183,36.354]]]}},                  
  {"type":"Feature","properties":{"EMD_CD":"47250116","EMD_ENG_NM":"Odae-dong","EMD_KOR_NM":"오대동"},"geometry":{"type":"Polygon","coordinates":[[[128.176,36.383],[128.183,36.361],[128.183,36.354],[128.154,36.381],[128.157,36.386],[128.176,36.383]]]}},                  
  {"type":"Feature","properties":{"EMD_CD":"47250117","EMD_ENG_NM":"Heunggak-dong","EMD_KOR_NM":"흥각동"},"geometry":{"type":"Polygon","coordinates":[[[128.174,36.387],[128.176,36.383],[128.157,36.386],[128.157,36.386],[128.162,36.393],[128.174,36.387]]]}},                  
  {"type":"Feature","properties":{"EMD_CD":"47250118","EMD_ENG_NM":"Geodong-dong","EMD_KOR_NM":"거동동"},"geometry":{"type":"Polygon","coordinates":[[[128.194,36.383],[128.183,36.361],[128.176,36.383],[128.174,36.387],[128.194,36.383]]]}},                  
  {"type":"Feature","properties":{"EMD_CD":"47250119","EMD_ENG_NM":"Inpyeong-dong","EMD_KOR_NM":"인평동"},"geometry":{"type":"Polygon","coordinates":[[[128.198,36.39],[128.194,36.383],[128.174,36.387],[128.162,36.393],[128.17,36.403],[128.172,36.401],[128.198,36.39]]]}},                  
  {"type":"Feature","properties":{"EMD_CD":"47250120","EMD_ENG_NM":"Seogok-dong","EMD_KOR_NM":"서곡동"},"geometry":{"type":"Polygon","coordinates":[[[128.195,36.407],[128.204,36.398],[128.198,36.39],[128.172,36.401],[128.195,36.407]]]}},                  
  {"type":"Feature","properties":{"EMD_CD":"47250121","EMD_ENG_NM":"Hwagae-dong","EMD_KOR_NM":"화개동"},"geometry":{"type":"Polygon","coordinates":[[[128.195,36.407],[128.172,36.401],[128.17,36.403],[128.171,36.403],[128.183,36.418],[128.188,36.42],[128.195,36.407]]]}},                  
  {"type":"Feature","properties":{"EMD_CD":"47250122","EMD_ENG_NM":"Oedap-dong","EMD_KOR_NM":"외답동"},"geometry":{"type":"Polygon","coordinates":[[[128.207,36.4],[128.204,36.398],[128.195,36.407],[128.188,36.42],[128.2,36.428],[128.207,36.4]]]}},                  
  {"type":"Feature","properties":{"EMD_CD":"47250123","EMD_ENG_NM":"Heonsin-dong","EMD_KOR_NM":"헌신동"},"geometry":{"type":"Polygon","coordinates":[[[128.222,36.423],[128.207,36.4],[128.2,36.428],[128.192,36.429],[128.198,36.434],[128.222,36.423]]]}},                  
  {"type":"Feature","properties":{"EMD_CD":"47250124","EMD_ENG_NM":"Byeongseong-dong","EMD_KOR_NM":"병성동"},"geometry":{"type":"Polygon","coordinates":[[[128.211,36.438],[128.228,36.437],[128.237,36.432],[128.233,36.426],[128.222,36.423],[128.198,36.434],[128.198,36.434],[128.211,36.438]]]}},                  
  {"type":"Feature","properties":{"EMD_CD":"47250125","EMD_ENG_NM":"Donam-dong","EMD_KOR_NM":"도남동"},"geometry":{"type":"Polygon","coordinates":[[[128.237,36.432],[128.228,36.437],[128.249,36.458],[128.237,36.432]]]}},                  
  {"type":"Feature","properties":{"EMD_CD":"47250126","EMD_ENG_NM":"Naksang-dong","EMD_KOR_NM":"낙상동"},"geometry":{"type":"Polygon","coordinates":[[[128.191,36.459],[128.192,36.459],[128.211,36.438],[128.198,36.434],[128.194,36.435],[128.186,36.46],[128.191,36.459]]]}},                  
  {"type":"Feature","properties":{"EMD_CD":"47250127","EMD_ENG_NM":"Jungdeok-dong","EMD_KOR_NM":"중덕동"},"geometry":{"type":"Polygon","coordinates":[[[128.183,36.46],[128.186,36.46],[128.194,36.435],[128.174,36.442],[128.177,36.445],[128.183,36.46]]]}},                  
  {"type":"Feature","properties":{"EMD_CD":"47250128","EMD_ENG_NM":"Chosan-dong","EMD_KOR_NM":"초산동"},"geometry":{"type":"Polygon","coordinates":[[[128.183,36.46],[128.177,36.445],[128.16,36.45],[128.168,36.465],[128.168,36.467],[128.175,36.466],[128.175,36.466],[128.183,36.46]]]}},                  
  {"type":"Feature","properties":{"EMD_CD":"47250129","EMD_ENG_NM":"Hwasan-dong","EMD_KOR_NM":"화산동"},"geometry":{"type":"Polygon","coordinates":[[[128.194,36.435],[128.198,36.434],[128.198,36.434],[128.192,36.429],[128.184,36.427],[128.159,36.432],[128.159,36.436],[128.174,36.442],[128.194,36.435]]]}},                  
  {"type":"Feature","properties":{"EMD_CD":"47250130","EMD_ENG_NM":"Gyesan-dong","EMD_KOR_NM":"계산동"},"geometry":{"type":"Polygon","coordinates":[[[128.184,36.427],[128.177,36.422],[128.158,36.428],[128.159,36.432],[128.184,36.427]]]}},                  
  {"type":"Feature","properties":{"EMD_CD":"47250131","EMD_ENG_NM":"Buwon-dong","EMD_KOR_NM":"부원동"},"geometry":{"type":"Polygon","coordinates":[[[128.16,36.45],[128.158,36.446],[128.143,36.443],[128.14,36.448],[128.142,36.455],[128.168,36.465],[128.16,36.45]]]}},                  
  {"type":"Feature","properties":{"EMD_CD":"47250132","EMD_ENG_NM":"Jukjeon-dong","EMD_KOR_NM":"죽전동"},"geometry":{"type":"Polygon","coordinates":[[[128.177,36.445],[128.174,36.442],[128.159,36.436],[128.158,36.446],[128.16,36.45],[128.177,36.445]]]}},                  
  {"type":"Feature","properties":{"EMD_CD":"47250133","EMD_ENG_NM":"Mansan-dong","EMD_KOR_NM":"만산동"},"geometry":{"type":"Polygon","coordinates":[[[128.158,36.446],[128.159,36.436],[128.159,36.432],[128.158,36.428],[128.146,36.42],[128.143,36.443],[128.158,36.446]]]}},                  
  {"type":"Feature","properties":{"EMD_CD":"47250134","EMD_ENG_NM":"Yeonwon-dong","EMD_KOR_NM":"연원동"},"geometry":{"type":"Polygon","coordinates":[[[128.14,36.448],[128.143,36.443],[128.146,36.42],[128.149,36.416],[128.133,36.413],[128.101,36.442],[128.14,36.448]]]}},                  
  {"type":"Feature","properties":{"EMD_CD":"47250135","EMD_ENG_NM":"Namjang-dong","EMD_KOR_NM":"남장동"},"geometry":{"type":"Polygon","coordinates":[[[128.133,36.413],[128.137,36.407],[128.115,36.396],[128.115,36.396],[128.097,36.439],[128.101,36.442],[128.133,36.413]]]}},                  
  {"type":"Feature","properties":{"EMD_CD":"47250136","EMD_ENG_NM":"Namjeok-dong","EMD_KOR_NM":"남적동"},"geometry":{"type":"Polygon","coordinates":[[[128.168,36.467],[128.168,36.465],[128.142,36.455],[128.168,36.467]]]}},                  
  {"type":"Feature","properties":{"EMD_CD":"47250250","EMD_ENG_NM":"Hamchang-eup","EMD_KOR_NM":"함창읍"},"geometry":{"type":"Polygon","coordinates":[[[128.156,36.6],[128.158,36.6],[128.159,36.6],[128.161,36.599],[128.161,36.598],[128.161,36.598],[128.162,36.597],[128.162,36.597],[128.164,36.597],[128.164,36.597],[128.165,36.597],[128.165,36.597],[128.167,36.597],[128.169,36.597],[128.169,36.597],[128.17,36.597],[128.171,36.597],[128.173,36.596],[128.173,36.596],[128.174,36.596],[128.174,36.596],[128.175,36.597],[128.175,36.597],[128.176,36.597],[128.177,36.596],[128.177,36.595],[128.177,36.595],[128.177,36.595],[128.177,36.594],[128.177,36.593],[128.177,36.592],[128.178,36.592],[128.179,36.592],[128.18,36.591],[128.18,36.59],[128.18,36.589],[128.18,36.589],[128.18,36.588],[128.179,36.587],[128.18,36.586],[128.181,36.585],[128.181,36.585],[128.18,36.585],[128.18,36.585],[128.18,36.584],[128.18,36.584],[128.18,36.584],[128.18,36.584],[128.179,36.584],[128.179,36.584],[128.178,36.584],[128.178,36.584],[128.178,36.584],[128.178,36.584],[128.179,36.584],[128.179,36.583],[128.179,36.583],[128.18,36.583],[128.18,36.583],[128.181,36.582],[128.181,36.582],[128.183,36.581],[128.183,36.581],[128.183,36.581],[128.184,36.581],[128.184,36.582],[128.184,36.582],[128.185,36.582],[128.185,36.582],[128.186,36.582],[128.186,36.582],[128.187,36.582],[128.187,36.583],[128.189,36.583],[128.189,36.583],[128.189,36.584],[128.189,36.584],[128.189,36.584],[128.19,36.584],[128.19,36.584],[128.19,36.584],[128.191,36.584],[128.191,36.583],[128.191,36.583],[128.192,36.583],[128.192,36.583],[128.193,36.583],[128.193,36.583],[128.193,36.583],[128.193,36.583],[128.194,36.583],[128.194,36.583],[128.194,36.583],[128.194,36.583],[128.194,36.582],[128.194,36.582],[128.194,36.582],[128.195,36.582],[128.195,36.582],[128.195,36.582],[128.196,36.582],[128.198,36.581],[128.198,36.581],[128.198,36.581],[128.199,36.581],[128.199,36.58],[128.199,36.58],[128.2,36.58],[128.2,36.58],[128.2,36.58],[128.201,36.58],[128.201,36.579],[128.201,36.579],[128.201,36.579],[128.202,36.579],[128.202,36.579],[128.202,36.579],[128.202,36.579],[128.202,36.579],[128.202,36.579],[128.202,36.579],[128.202,36.579],[128.203,36.579],[128.203,36.579],[128.203,36.579],[128.204,36.579],[128.204,36.579],[128.206,36.579],[128.207,36.578],[128.208,36.578],[128.208,36.577],[128.208,36.577],[128.208,36.577],[128.207,36.576],[128.207,36.576],[128.207,36.576],[128.207,36.575],[128.206,36.575],[128.206,36.575],[128.206,36.575],[128.206,36.575],[128.206,36.575],[128.206,36.574],[128.206,36.573],[128.206,36.572],[128.206,36.572],[128.207,36.572],[128.207,36.572],[128.207,36.572],[128.207,36.572],[128.207,36.572],[128.207,36.572],[128.207,36.572],[128.208,36.572],[128.208,36.572],[128.209,36.573],[128.209,36.573],[128.209,36.573],[128.21,36.573],[128.21,36.573],[128.21,36.573],[128.211,36.573],[128.212,36.573],[128.212,36.573],[128.213,36.573],[128.213,36.573],[128.213,36.573],[128.213,36.573],[128.213,36.573],[128.214,36.573],[128.214,36.573],[128.215,36.573],[128.215,36.573],[128.215,36.573],[128.216,36.573],[128.216,36.573],[128.216,36.573],[128.218,36.573],[128.218,36.573],[128.219,36.574],[128.219,36.574],[128.219,36.574],[128.219,36.572],[128.22,36.572],[128.22,36.571],[128.22,36.571],[128.22,36.571],[128.22,36.57],[128.22,36.57],[128.22,36.569],[128.22,36.569],[128.219,36.568],[128.219,36.568],[128.219,36.567],[128.218,36.566],[128.218,36.566],[128.218,36.565],[128.218,36.565],[128.218,36.565],[128.218,36.565],[128.217,36.564],[128.217,36.564],[128.217,36.564],[128.217,36.563],[128.217,36.563],[128.216,36.562],[128.217,36.56],[128.217,36.558],[128.219,36.557],[128.218,36.557],[128.218,36.557],[128.217,36.557],[128.217,36.555],[128.218,36.554],[128.218,36.551],[128.217,36.55],[128.217,36.55],[128.217,36.549],[128.217,36.549],[128.217,36.548],[128.216,36.548],[128.216,36.547],[128.216,36.546],[128.217,36.545],[128.217,36.544],[128.217,36.542],[128.217,36.541],[128.217,36.541],[128.218,36.538],[128.219,36.538],[128.22,36.537],[128.222,36.535],[128.224,36.534],[128.225,36.534],[128.227,36.533],[128.228,36.533],[128.228,36.533],[128.229,36.533],[128.233,36.531],[128.233,36.531],[128.234,36.531],[128.234,36.53],[128.235,36.53],[128.236,36.53],[128.238,36.531],[128.239,36.532],[128.241,36.532],[128.243,36.533],[128.244,36.533],[128.245,36.533],[128.247,36.533],[128.247,36.534],[128.249,36.535],[128.25,36.535],[128.252,36.535],[128.253,36.535],[128.254,36.535],[128.25,36.509],[128.184,36.518],[128.175,36.541],[128.151,36.6],[128.152,36.599],[128.156,36.6]]]}},                  
  {"type":"Feature","properties":{"EMD_CD":"47250310","EMD_ENG_NM":"Jungdong-myeon","EMD_KOR_NM":"중동면"},"geometry":{"type":"Polygon","coordinates":[[[128.314,36.455],[128.322,36.445],[128.322,36.445],[128.322,36.445],[128.322,36.445],[128.324,36.444],[128.324,36.443],[128.324,36.443],[128.323,36.424],[128.324,36.424],[128.327,36.424],[128.327,36.424],[128.327,36.424],[128.327,36.424],[128.327,36.424],[128.328,36.424],[128.328,36.424],[128.328,36.424],[128.328,36.424],[128.328,36.424],[128.328,36.424],[128.329,36.424],[128.329,36.424],[128.329,36.424],[128.329,36.424],[128.33,36.423],[128.33,36.423],[128.33,36.423],[128.334,36.42],[128.333,36.418],[128.333,36.417],[128.333,36.415],[128.337,36.409],[128.337,36.409],[128.338,36.408],[128.338,36.408],[128.339,36.407],[128.339,36.406],[128.339,36.404],[128.333,36.399],[128.333,36.399],[128.329,36.389],[128.327,36.387],[128.326,36.386],[128.324,36.386],[128.323,36.385],[128.317,36.388],[128.318,36.389],[128.318,36.391],[128.233,36.426],[128.237,36.432],[128.249,36.458],[128.262,36.477],[128.314,36.455]]]}},                  
  {"type":"Feature","properties":{"EMD_CD":"47250320","EMD_ENG_NM":"Sabeol-myeon","EMD_KOR_NM":"사벌면"},"geometry":{"type":"Polygon","coordinates":[[[128.268,36.532],[128.268,36.531],[128.268,36.531],[128.269,36.529],[128.27,36.525],[128.27,36.524],[128.268,36.517],[128.267,36.516],[128.266,36.514],[128.266,36.512],[128.265,36.511],[128.262,36.477],[128.249,36.458],[128.228,36.437],[128.211,36.438],[128.192,36.459],[128.191,36.459],[128.186,36.46],[128.183,36.46],[128.175,36.466],[128.175,36.466],[128.168,36.467],[128.178,36.511],[128.184,36.518],[128.25,36.509],[128.254,36.535],[128.257,36.535],[128.26,36.534],[128.261,36.534],[128.261,36.534],[128.266,36.532],[128.267,36.533],[128.268,36.536],[128.268,36.532]]]}},                  
  {"type":"Feature","properties":{"EMD_CD":"47250330","EMD_ENG_NM":"Nakdong-myeon","EMD_KOR_NM":"낙동면"},"geometry":{"type":"Polygon","coordinates":[[[128.318,36.391],[128.318,36.389],[128.317,36.388],[128.317,36.387],[128.315,36.384],[128.312,36.371],[128.308,36.361],[128.307,36.363],[128.307,36.363],[128.307,36.363],[128.305,36.362],[128.305,36.361],[128.304,36.361],[128.304,36.361],[128.304,36.36],[128.3,36.357],[128.299,36.355],[128.298,36.354],[128.298,36.354],[128.297,36.353],[128.293,36.351],[128.291,36.35],[128.291,36.35],[128.29,36.348],[128.289,36.348],[128.288,36.346],[128.282,36.346],[128.282,36.349],[128.282,36.349],[128.277,36.35],[128.278,36.357],[128.27,36.362],[128.258,36.362],[128.256,36.36],[128.253,36.359],[128.251,36.357],[128.233,36.333],[128.229,36.308],[128.213,36.305],[128.212,36.303],[128.208,36.301],[128.207,36.299],[128.206,36.299],[128.199,36.298],[128.197,36.298],[128.195,36.3],[128.193,36.3],[128.192,36.3],[128.19,36.301],[128.19,36.301],[128.189,36.301],[128.187,36.298],[128.186,36.298],[128.183,36.298],[128.181,36.298],[128.179,36.298],[128.178,36.298],[128.173,36.298],[128.172,36.298],[128.172,36.299],[128.174,36.333],[128.183,36.354],[128.183,36.361],[128.194,36.383],[128.198,36.39],[128.204,36.398],[128.207,36.4],[128.222,36.423],[128.233,36.426],[128.318,36.391]]]}},                  
  {"type":"Feature","properties":{"EMD_CD":"47250340","EMD_ENG_NM":"Cheongni-myeon","EMD_KOR_NM":"청리면"},"geometry":{"type":"Polygon","coordinates":[[[128.135,36.366],[128.159,36.342],[128.171,36.335],[128.173,36.334],[128.174,36.333],[128.172,36.299],[128.171,36.3],[128.17,36.3],[128.163,36.297],[128.157,36.295],[128.154,36.294],[128.12,36.31],[128.119,36.31],[128.091,36.326],[128.119,36.371],[128.135,36.366]]]}},                  
  {"type":"Feature","properties":{"EMD_CD":"47250350","EMD_ENG_NM":"Gongseong-myeon","EMD_KOR_NM":"공성면"},"geometry":{"type":"Polygon","coordinates":[[[128.035,36.35],[128.039,36.348],[128.039,36.348],[128.046,36.342],[128.091,36.326],[128.119,36.31],[128.12,36.31],[128.154,36.294],[128.154,36.293],[128.152,36.291],[128.15,36.29],[128.146,36.289],[128.139,36.285],[128.138,36.283],[128.137,36.281],[128.137,36.28],[128.137,36.281],[128.137,36.281],[128.137,36.281],[128.137,36.281],[128.137,36.281],[128.137,36.281],[128.137,36.281],[128.137,36.28],[128.137,36.28],[128.137,36.28],[128.138,36.28],[128.137,36.28],[128.136,36.279],[128.135,36.276],[128.134,36.274],[128.133,36.272],[128.133,36.268],[128.134,36.266],[128.137,36.263],[128.137,36.262],[128.137,36.261],[128.137,36.259],[128.137,36.258],[128.137,36.257],[128.05,36.244],[128.011,36.272],[128.031,36.346],[128.035,36.35]]]}},                  
  {"type":"Feature","properties":{"EMD_CD":"47250360","EMD_ENG_NM":"Oenam-myeon","EMD_KOR_NM":"외남면"},"geometry":{"type":"Polygon","coordinates":[[[128.12,36.371],[128.119,36.371],[128.091,36.326],[128.046,36.342],[128.087,36.389],[128.088,36.389],[128.115,36.396],[128.115,36.396],[128.12,36.371]]]}},                  
  {"type":"Feature","properties":{"EMD_CD":"47250370","EMD_ENG_NM":"Naeseo-myeon","EMD_KOR_NM":"내서면"},"geometry":{"type":"Polygon","coordinates":[[[128.097,36.439],[128.115,36.396],[128.088,36.389],[128.087,36.389],[128.046,36.342],[128.039,36.348],[128.039,36.348],[128.035,36.35],[128.002,36.386],[127.994,36.435],[128.007,36.458],[128.097,36.439]]]}},                  
  {"type":"Feature","properties":{"EMD_CD":"47250380","EMD_ENG_NM":"Modong-myeon","EMD_KOR_NM":"모동면"},"geometry":{"type":"Polygon","coordinates":[[[128.031,36.346],[128.011,36.272],[127.991,36.263],[127.981,36.264],[127.978,36.255],[127.972,36.252],[127.971,36.25],[127.969,36.25],[127.968,36.25],[127.968,36.251],[127.968,36.251],[127.966,36.252],[127.966,36.252],[127.966,36.252],[127.966,36.252],[127.966,36.252],[127.966,36.252],[127.965,36.253],[127.965,36.253],[127.96,36.252],[127.956,36.255],[127.956,36.256],[127.955,36.257],[127.955,36.257],[127.955,36.257],[127.949,36.257],[127.948,36.257],[127.948,36.258],[127.948,36.259],[127.948,36.259],[127.949,36.261],[127.948,36.263],[127.948,36.265],[127.948,36.265],[127.948,36.266],[127.947,36.267],[127.945,36.267],[127.944,36.267],[127.943,36.267],[127.931,36.278],[127.926,36.279],[127.926,36.28],[127.925,36.279],[127.924,36.279],[127.907,36.286],[127.906,36.289],[127.906,36.291],[127.906,36.299],[127.905,36.3],[127.905,36.301],[127.904,36.301],[127.921,36.327],[128.031,36.346]]]}},                  
  {"type":"Feature","properties":{"EMD_CD":"47250390","EMD_ENG_NM":"Moseo-myeon","EMD_KOR_NM":"모서면"},"geometry":{"type":"Polygon","coordinates":[[[128.035,36.35],[128.031,36.346],[127.921,36.327],[127.904,36.301],[127.904,36.301],[127.903,36.301],[127.902,36.3],[127.901,36.299],[127.9,36.298],[127.898,36.298],[127.892,36.292],[127.883,36.274],[127.861,36.277],[127.861,36.277],[127.861,36.277],[127.861,36.277],[127.86,36.277],[127.86,36.276],[127.86,36.276],[127.86,36.276],[127.86,36.276],[127.86,36.276],[127.859,36.276],[127.859,36.276],[127.858,36.276],[127.855,36.275],[127.854,36.275],[127.854,36.275],[127.853,36.274],[127.852,36.274],[127.851,36.274],[127.851,36.274],[127.851,36.275],[127.851,36.277],[127.85,36.281],[127.849,36.289],[127.846,36.295],[127.847,36.301],[127.842,36.308],[127.841,36.31],[127.843,36.312],[127.844,36.313],[127.845,36.313],[127.845,36.314],[127.844,36.315],[127.844,36.315],[127.845,36.316],[127.845,36.316],[127.845,36.317],[127.846,36.317],[127.846,36.318],[127.846,36.318],[127.847,36.318],[127.849,36.319],[127.849,36.319],[127.849,36.32],[127.85,36.32],[127.852,36.324],[127.851,36.325],[127.851,36.325],[127.851,36.326],[127.851,36.326],[127.851,36.326],[127.851,36.327],[127.852,36.327],[127.852,36.327],[127.852,36.329],[127.853,36.33],[127.853,36.33],[127.852,36.33],[127.853,36.331],[127.853,36.332],[127.853,36.332],[127.854,36.332],[127.854,36.332],[127.854,36.332],[127.854,36.331],[127.854,36.331],[127.854,36.331],[127.855,36.331],[127.855,36.331],[127.856,36.331],[127.856,36.331],[127.857,36.331],[127.864,36.335],[127.866,36.336],[127.866,36.337],[127.867,36.337],[127.867,36.337],[127.868,36.337],[127.868,36.338],[127.868,36.338],[127.868,36.338],[127.868,36.338],[127.868,36.339],[127.869,36.339],[127.869,36.339],[127.869,36.339],[127.87,36.34],[127.87,36.343],[127.874,36.345],[127.875,36.345],[127.877,36.346],[127.883,36.346],[127.886,36.35],[127.885,36.352],[127.885,36.354],[127.886,36.355],[127.891,36.357],[127.891,36.36],[127.954,36.361],[128.002,36.386],[128.035,36.35]]]}},                  
  {"type":"Feature","properties":{"EMD_CD":"47250400","EMD_ENG_NM":"Hwadong-myeon","EMD_KOR_NM":"화동면"},"geometry":{"type":"Polygon","coordinates":[[[127.994,36.435],[128.002,36.386],[127.954,36.361],[127.891,36.36],[127.887,36.364],[127.886,36.365],[127.886,36.366],[127.885,36.366],[127.885,36.369],[127.884,36.371],[127.883,36.371],[127.882,36.371],[127.88,36.371],[127.88,36.371],[127.88,36.372],[127.88,36.372],[127.883,36.374],[127.883,36.377],[127.883,36.378],[127.884,36.379],[127.884,36.379],[127.885,36.379],[127.887,36.38],[127.888,36.381],[127.89,36.381],[127.894,36.389],[127.91,36.396],[127.938,36.4],[127.994,36.435]]]}},                  
  {"type":"Feature","properties":{"EMD_CD":"47250410","EMD_ENG_NM":"Hwaseo-myeon","EMD_KOR_NM":"화서면"},"geometry":{"type":"Polygon","coordinates":[[[128.007,36.458],[127.994,36.435],[127.938,36.4],[127.894,36.429],[127.938,36.507],[127.951,36.511],[128.007,36.458]]]}},                  
  {"type":"Feature","properties":{"EMD_CD":"47250420","EMD_ENG_NM":"Hwabuk-myeon","EMD_KOR_NM":"화북면"},"geometry":{"type":"Polygon","coordinates":[[[127.924,36.602],[127.924,36.6],[127.928,36.595],[127.931,36.592],[127.932,36.592],[127.932,36.592],[127.932,36.592],[127.933,36.591],[127.933,36.591],[127.933,36.591],[127.933,36.59],[127.933,36.585],[127.933,36.584],[127.933,36.583],[127.933,36.583],[127.933,36.582],[127.932,36.582],[127.932,36.582],[127.931,36.581],[127.931,36.581],[127.931,36.581],[127.931,36.58],[127.931,36.579],[127.931,36.579],[127.931,36.578],[127.931,36.578],[127.931,36.577],[127.932,36.576],[127.932,36.576],[127.932,36.575],[127.933,36.575],[127.933,36.575],[127.934,36.575],[127.934,36.575],[127.934,36.575],[127.934,36.574],[127.934,36.574],[127.935,36.573],[127.935,36.572],[127.936,36.572],[127.936,36.571],[127.936,36.571],[127.937,36.571],[127.937,36.57],[127.937,36.564],[127.934,36.56],[127.933,36.558],[127.934,36.557],[127.934,36.557],[127.935,36.556],[127.937,36.554],[127.94,36.549],[127.936,36.546],[127.936,36.544],[127.936,36.543],[127.937,36.54],[127.937,36.539],[127.938,36.538],[127.931,36.536],[127.931,36.535],[127.931,36.535],[127.931,36.534],[127.931,36.534],[127.931,36.534],[127.931,36.533],[127.931,36.533],[127.932,36.533],[127.932,36.533],[127.932,36.533],[127.932,36.533],[127.932,36.532],[127.932,36.532],[127.932,36.532],[127.933,36.532],[127.933,36.532],[127.933,36.532],[127.933,36.532],[127.933,36.532],[127.933,36.531],[127.933,36.531],[127.934,36.531],[127.934,36.531],[127.934,36.53],[127.934,36.53],[127.935,36.53],[127.935,36.529],[127.935,36.529],[127.936,36.529],[127.936,36.529],[127.936,36.529],[127.937,36.528],[127.937,36.528],[127.937,36.528],[127.937,36.528],[127.938,36.527],[127.938,36.527],[127.939,36.527],[127.939,36.527],[127.94,36.526],[127.94,36.526],[127.94,36.526],[127.94,36.526],[127.941,36.526],[127.941,36.526],[127.942,36.526],[127.942,36.526],[127.943,36.526],[127.943,36.526],[127.944,36.526],[127.944,36.525],[127.944,36.525],[127.944,36.526],[127.949,36.524],[127.948,36.522],[127.948,36.515],[127.951,36.511],[127.938,36.507],[127.928,36.514],[127.914,36.511],[127.913,36.508],[127.909,36.509],[127.907,36.508],[127.906,36.507],[127.906,36.508],[127.905,36.508],[127.905,36.509],[127.905,36.509],[127.905,36.509],[127.904,36.51],[127.903,36.511],[127.903,36.513],[127.903,36.517],[127.901,36.525],[127.903,36.527],[127.899,36.53],[127.897,36.531],[127.897,36.531],[127.897,36.531],[127.896,36.531],[127.879,36.535],[127.87,36.543],[127.87,36.559],[127.86,36.568],[127.845,36.569],[127.83,36.574],[127.824,36.571],[127.824,36.571],[127.824,36.572],[127.822,36.573],[127.82,36.574],[127.819,36.574],[127.818,36.575],[127.818,36.575],[127.818,36.575],[127.817,36.576],[127.817,36.576],[127.817,36.577],[127.817,36.577],[127.816,36.578],[127.813,36.58],[127.812,36.579],[127.812,36.579],[127.811,36.579],[127.81,36.58],[127.81,36.58],[127.809,36.58],[127.809,36.58],[127.809,36.58],[127.808,36.58],[127.808,36.58],[127.807,36.581],[127.806,36.581],[127.806,36.581],[127.806,36.581],[127.806,36.581],[127.805,36.581],[127.805,36.581],[127.805,36.583],[127.804,36.583],[127.804,36.583],[127.803,36.584],[127.802,36.584],[127.802,36.584],[127.801,36.585],[127.8,36.586],[127.799,36.586],[127.798,36.586],[127.798,36.587],[127.799,36.588],[127.8,36.589],[127.799,36.59],[127.797,36.593],[127.796,36.595],[127.797,36.596],[127.797,36.597],[127.797,36.6],[127.798,36.601],[127.798,36.602],[127.798,36.602],[127.799,36.602],[127.802,36.602],[127.806,36.604],[127.808,36.606],[127.813,36.608],[127.819,36.608],[127.823,36.612],[127.841,36.609],[127.848,36.625],[127.874,36.655],[127.909,36.626],[127.911,36.615],[127.919,36.609],[127.92,36.601],[127.921,36.602],[127.922,36.602],[127.923,36.602],[127.924,36.602]]]}},                  
  {"type":"Feature","properties":{"EMD_CD":"47250430","EMD_ENG_NM":"Oeseo-myeon","EMD_KOR_NM":"외서면"},"geometry":{"type":"Polygon","coordinates":[[[127.96,36.522],[127.96,36.522],[127.96,36.521],[127.961,36.521],[127.961,36.521],[127.961,36.521],[127.961,36.521],[127.961,36.521],[127.962,36.52],[127.962,36.52],[127.962,36.52],[127.963,36.52],[127.965,36.519],[127.966,36.519],[127.966,36.518],[127.966,36.518],[127.966,36.518],[127.966,36.518],[127.966,36.518],[127.967,36.518],[127.967,36.518],[127.967,36.517],[127.967,36.517],[127.967,36.517],[127.967,36.517],[127.967,36.517],[127.968,36.517],[127.968,36.517],[127.969,36.516],[127.971,36.516],[127.973,36.515],[127.974,36.515],[127.975,36.515],[127.978,36.513],[127.98,36.514],[128.094,36.51],[128.127,36.479],[128.178,36.511],[128.168,36.467],[128.142,36.455],[128.14,36.448],[128.101,36.442],[128.097,36.439],[128.007,36.458],[127.951,36.511],[127.948,36.515],[127.948,36.522],[127.949,36.524],[127.949,36.524],[127.953,36.523],[127.957,36.524],[127.958,36.524],[127.958,36.524],[127.958,36.524],[127.959,36.524],[127.959,36.524],[127.958,36.524],[127.958,36.523],[127.96,36.522]]]}},                  
  {"type":"Feature","properties":{"EMD_CD":"47250440","EMD_ENG_NM":"Euncheok-myeon","EMD_KOR_NM":"은척면"},"geometry":{"type":"Polygon","coordinates":[[[128.076,36.606],[128.076,36.606],[128.09,36.58],[128.09,36.58],[128.093,36.536],[128.094,36.51],[127.98,36.514],[127.98,36.515],[127.978,36.519],[127.978,36.521],[127.98,36.525],[127.98,36.526],[127.981,36.526],[127.981,36.528],[127.981,36.528],[127.98,36.53],[127.979,36.531],[127.978,36.533],[127.979,36.534],[127.98,36.535],[127.981,36.535],[127.981,36.535],[127.981,36.536],[127.981,36.537],[127.981,36.537],[127.981,36.538],[127.98,36.54],[127.98,36.541],[127.979,36.542],[127.979,36.543],[127.982,36.545],[127.983,36.545],[127.986,36.545],[127.989,36.545],[127.993,36.545],[127.995,36.547],[127.995,36.547],[127.995,36.547],[127.997,36.549],[127.998,36.55],[128.002,36.55],[128.002,36.55],[128.003,36.55],[128.005,36.551],[128.006,36.551],[128.006,36.55],[128.007,36.55],[128.008,36.549],[128.01,36.549],[128.011,36.548],[128.012,36.547],[128.013,36.547],[128.014,36.546],[128.016,36.545],[128.017,36.544],[128.02,36.545],[128.022,36.545],[128.023,36.545],[128.024,36.545],[128.026,36.546],[128.027,36.546],[128.027,36.547],[128.03,36.547],[128.031,36.548],[128.033,36.548],[128.034,36.548],[128.036,36.548],[128.037,36.548],[128.039,36.548],[128.039,36.548],[128.04,36.548],[128.04,36.548],[128.04,36.548],[128.041,36.548],[128.042,36.548],[128.042,36.548],[128.042,36.548],[128.043,36.548],[128.043,36.548],[128.043,36.548],[128.043,36.548],[128.043,36.548],[128.043,36.548],[128.044,36.547],[128.044,36.547],[128.044,36.547],[128.044,36.547],[128.044,36.547],[128.044,36.547],[128.044,36.547],[128.044,36.547],[128.045,36.547],[128.045,36.547],[128.045,36.547],[128.045,36.547],[128.045,36.547],[128.046,36.547],[128.046,36.547],[128.046,36.547],[128.046,36.547],[128.046,36.547],[128.047,36.547],[128.047,36.547],[128.047,36.546],[128.047,36.546],[128.047,36.546],[128.047,36.546],[128.047,36.546],[128.048,36.547],[128.048,36.547],[128.048,36.547],[128.048,36.546],[128.049,36.546],[128.049,36.546],[128.049,36.546],[128.049,36.546],[128.049,36.546],[128.049,36.546],[128.049,36.546],[128.049,36.546],[128.05,36.546],[128.05,36.546],[128.05,36.546],[128.05,36.546],[128.05,36.546],[128.051,36.546],[128.051,36.546],[128.051,36.546],[128.051,36.546],[128.051,36.546],[128.051,36.546],[128.051,36.546],[128.051,36.546],[128.051,36.546],[128.051,36.546],[128.051,36.546],[128.052,36.546],[128.052,36.546],[128.052,36.546],[128.052,36.546],[128.052,36.546],[128.053,36.546],[128.053,36.546],[128.053,36.546],[128.053,36.546],[128.053,36.546],[128.054,36.546],[128.054,36.546],[128.054,36.546],[128.054,36.546],[128.054,36.546],[128.054,36.547],[128.054,36.547],[128.055,36.547],[128.055,36.547],[128.055,36.547],[128.055,36.547],[128.055,36.547],[128.055,36.547],[128.056,36.547],[128.056,36.547],[128.056,36.547],[128.056,36.547],[128.056,36.548],[128.056,36.548],[128.055,36.549],[128.055,36.55],[128.055,36.55],[128.055,36.55],[128.056,36.55],[128.056,36.55],[128.056,36.55],[128.056,36.55],[128.056,36.55],[128.057,36.551],[128.057,36.552],[128.057,36.553],[128.057,36.554],[128.058,36.554],[128.059,36.555],[128.059,36.556],[128.058,36.556],[128.059,36.557],[128.059,36.558],[128.06,36.558],[128.061,36.56],[128.062,36.561],[128.063,36.561],[128.063,36.561],[128.065,36.561],[128.065,36.561],[128.066,36.561],[128.066,36.562],[128.065,36.564],[128.064,36.565],[128.064,36.567],[128.062,36.568],[128.061,36.569],[128.062,36.57],[128.061,36.57],[128.061,36.571],[128.061,36.571],[128.061,36.572],[128.061,36.573],[128.059,36.575],[128.058,36.576],[128.059,36.577],[128.058,36.578],[128.057,36.578],[128.057,36.579],[128.058,36.58],[128.056,36.582],[128.056,36.583],[128.057,36.583],[128.058,36.584],[128.057,36.585],[128.058,36.586],[128.059,36.586],[128.061,36.587],[128.061,36.587],[128.062,36.587],[128.063,36.587],[128.062,36.588],[128.062,36.588],[128.062,36.588],[128.062,36.588],[128.062,36.588],[128.062,36.588],[128.062,36.588],[128.061,36.588],[128.061,36.589],[128.062,36.589],[128.062,36.589],[128.062,36.589],[128.062,36.589],[128.062,36.589],[128.062,36.589],[128.063,36.589],[128.063,36.589],[128.063,36.589],[128.063,36.589],[128.064,36.589],[128.064,36.589],[128.064,36.589],[128.064,36.589],[128.065,36.589],[128.065,36.589],[128.065,36.589],[128.065,36.59],[128.065,36.59],[128.065,36.59],[128.065,36.59],[128.066,36.59],[128.066,36.59],[128.066,36.591],[128.066,36.591],[128.066,36.591],[128.066,36.591],[128.066,36.591],[128.067,36.591],[128.067,36.591],[128.067,36.591],[128.067,36.592],[128.067,36.592],[128.067,36.592],[128.067,36.592],[128.067,36.592],[128.067,36.592],[128.067,36.592],[128.067,36.592],[128.068,36.592],[128.068,36.592],[128.068,36.593],[128.068,36.593],[128.068,36.593],[128.068,36.593],[128.068,36.593],[128.068,36.593],[128.068,36.593],[128.068,36.593],[128.068,36.594],[128.069,36.594],[128.069,36.594],[128.069,36.594],[128.069,36.594],[128.069,36.594],[128.069,36.594],[128.069,36.594],[128.069,36.594],[128.069,36.595],[128.069,36.595],[128.069,36.595],[128.069,36.595],[128.069,36.595],[128.069,36.595],[128.069,36.595],[128.069,36.595],[128.069,36.596],[128.069,36.596],[128.069,36.596],[128.069,36.596],[128.069,36.596],[128.069,36.596],[128.069,36.596],[128.069,36.597],[128.069,36.597],[128.069,36.597],[128.069,36.597],[128.07,36.597],[128.07,36.597],[128.07,36.597],[128.07,36.597],[128.07,36.597],[128.07,36.597],[128.07,36.597],[128.07,36.598],[128.07,36.598],[128.07,36.598],[128.07,36.598],[128.07,36.598],[128.071,36.598],[128.071,36.598],[128.072,36.598],[128.072,36.599],[128.072,36.599],[128.072,36.599],[128.072,36.599],[128.072,36.601],[128.072,36.602],[128.072,36.604],[128.072,36.605],[128.073,36.606],[128.074,36.606],[128.076,36.606]]]}},                  
  {"type":"Feature","properties":{"EMD_CD":"47250450","EMD_ENG_NM":"Gonggeom-myeon","EMD_KOR_NM":"공검면"},"geometry":{"type":"Polygon","coordinates":[[[128.175,36.541],[128.184,36.518],[128.178,36.511],[128.127,36.479],[128.094,36.51],[128.093,36.536],[128.175,36.541]]]}},                  
  {"type":"Feature","properties":{"EMD_CD":"47250460","EMD_ENG_NM":"Ian-myeon","EMD_KOR_NM":"이안면"},"geometry":{"type":"Polygon","coordinates":[[[128.146,36.606],[128.147,36.605],[128.147,36.604],[128.15,36.6],[128.151,36.6],[128.175,36.541],[128.093,36.536],[128.09,36.58],[128.09,36.58],[128.076,36.606],[128.076,36.606],[128.077,36.607],[128.08,36.607],[128.082,36.608],[128.084,36.609],[128.085,36.609],[128.089,36.609],[128.089,36.609],[128.091,36.609],[128.092,36.608],[128.094,36.609],[128.095,36.609],[128.098,36.608],[128.099,36.609],[128.1,36.608],[128.103,36.608],[128.108,36.608],[128.109,36.61],[128.111,36.611],[128.112,36.612],[128.112,36.614],[128.113,36.618],[128.113,36.619],[128.113,36.619],[128.114,36.62],[128.116,36.621],[128.12,36.622],[128.122,36.62],[128.123,36.62],[128.125,36.619],[128.13,36.614],[128.131,36.614],[128.133,36.613],[128.135,36.613],[128.136,36.612],[128.138,36.611],[128.141,36.609],[128.145,36.608],[128.146,36.606]]]}},                  
  {"type":"Feature","properties":{"EMD_CD":"47250470","EMD_ENG_NM":"Hwanam-myeon","EMD_KOR_NM":"화남면"},"geometry":{"type":"Polygon","coordinates":[[[127.938,36.507],[127.894,36.429],[127.938,36.4],[127.91,36.396],[127.894,36.389],[127.89,36.381],[127.888,36.381],[127.887,36.38],[127.885,36.379],[127.884,36.379],[127.884,36.38],[127.884,36.38],[127.884,36.38],[127.883,36.381],[127.883,36.381],[127.883,36.381],[127.883,36.382],[127.882,36.382],[127.879,36.383],[127.878,36.386],[127.879,36.386],[127.877,36.389],[127.875,36.391],[127.872,36.391],[127.87,36.392],[127.869,36.391],[127.867,36.392],[127.866,36.392],[127.865,36.392],[127.865,36.391],[127.864,36.392],[127.864,36.393],[127.863,36.393],[127.863,36.393],[127.863,36.393],[127.863,36.393],[127.863,36.393],[127.863,36.393],[127.863,36.393],[127.863,36.393],[127.863,36.394],[127.866,36.395],[127.864,36.4],[127.864,36.403],[127.865,36.403],[127.867,36.403],[127.87,36.404],[127.87,36.404],[127.87,36.404],[127.87,36.404],[127.87,36.404],[127.871,36.404],[127.872,36.405],[127.873,36.406],[127.873,36.406],[127.873,36.406],[127.873,36.406],[127.873,36.406],[127.874,36.407],[127.873,36.407],[127.874,36.407],[127.873,36.408],[127.873,36.41],[127.875,36.411],[127.876,36.413],[127.876,36.413],[127.876,36.414],[127.876,36.414],[127.876,36.414],[127.879,36.417],[127.88,36.419],[127.88,36.419],[127.881,36.419],[127.881,36.42],[127.881,36.42],[127.882,36.421],[127.882,36.421],[127.883,36.422],[127.883,36.422],[127.883,36.424],[127.883,36.424],[127.883,36.424],[127.882,36.424],[127.881,36.424],[127.879,36.424],[127.879,36.424],[127.878,36.424],[127.878,36.424],[127.877,36.424],[127.876,36.424],[127.875,36.424],[127.875,36.424],[127.874,36.424],[127.873,36.424],[127.873,36.425],[127.874,36.426],[127.876,36.428],[127.874,36.438],[127.873,36.44],[127.873,36.44],[127.873,36.44],[127.873,36.44],[127.873,36.44],[127.872,36.441],[127.872,36.441],[127.872,36.441],[127.872,36.441],[127.872,36.441],[127.872,36.441],[127.872,36.441],[127.871,36.441],[127.871,36.441],[127.871,36.441],[127.871,36.442],[127.871,36.442],[127.872,36.442],[127.872,36.442],[127.872,36.442],[127.872,36.442],[127.873,36.442],[127.873,36.442],[127.873,36.442],[127.873,36.442],[127.873,36.442],[127.873,36.442],[127.873,36.442],[127.873,36.442],[127.873,36.443],[127.873,36.443],[127.874,36.443],[127.873,36.445],[127.874,36.447],[127.875,36.449],[127.88,36.454],[127.879,36.458],[127.88,36.459],[127.881,36.461],[127.882,36.462],[127.881,36.481],[127.878,36.481],[127.877,36.482],[127.875,36.483],[127.876,36.488],[127.88,36.493],[127.881,36.493],[127.882,36.493],[127.883,36.493],[127.884,36.493],[127.885,36.494],[127.889,36.493],[127.89,36.495],[127.893,36.496],[127.895,36.498],[127.901,36.5],[127.905,36.504],[127.905,36.505],[127.906,36.506],[127.906,36.507],[127.906,36.507],[127.907,36.508],[127.909,36.509],[127.913,36.508],[127.914,36.511],[127.928,36.514],[127.938,36.507]]]}}             
]}